bobtools/__init__.py
bobtools/__version__.py
bobtools/entry_points.py
bobtools/mlflow.py
bobtools/seldon.py
tests/__init__.py
tests/conftest.py
tests/test_curves.py
Bobtools-0.1.25.dist-info/LICENSE
Bobtools-0.1.25.dist-info/METADATA
Bobtools-0.1.25.dist-info/WHEEL
Bobtools-0.1.25.dist-info/entry_points.txt
Bobtools-0.1.25.dist-info/top_level.txt
Bobtools-0.1.25.dist-info/RECORD
