Metadata-Version: 2.1
Name: Bobtools
Version: 0.1.25
Summary: Bobtools with utility functions for the Bob Best of Breed AI platform
Home-page: https://github.com/bjelkenhed/bobtools
Author: Magnus Bjelkenhed
Author-email: bjelkenhed@gmail.com
License: Apache 2.0
Keywords: bobtools
Classifier: Development Status :: 4 - Beta
Classifier: Intended Audience :: Developers
Classifier: Programming Language :: Python :: 3.8
Requires-Python: >=3.8.*
License-File: LICENSE
